cache_alchemy/__init__.py
cache_alchemy/config.py
cache_alchemy/dependency.py
cache_alchemy/link.py
cache_alchemy/lru.py
cache_alchemy/utils.py
cache_alchemy/backends/__init__.py
cache_alchemy/backends/base.py
cache_alchemy/backends/json.py
cache_alchemy/backends/memory.py
cache_alchemy/backends/pickle.py
cache_alchemy-0.4.5.dist-info/AUTHORS.rst
cache_alchemy-0.4.5.dist-info/METADATA
cache_alchemy-0.4.5.dist-info/WHEEL
cache_alchemy-0.4.5.dist-info/top_level.txt
cache_alchemy-0.4.5.dist-info/RECORD
