Metadata-Version: 2.1
Name: cache-alchemy
Version: 0.4.5
Summary: The Python Cache Toolkit.
Home-page: https://github.com/GuangTianLi/cache-alchemy
Author: GuangTian Li
Author-email: guangtian_li@qq.com
License: UNKNOWN
Keywords: cache-alchemy
Platform: UNKNOWN
Classifier: Development Status :: 2 - Pre-Alpha
Classifier: Intended Audience :: Developers
Classifier: Natural Language :: English
Classifier: Programming Language :: Python :: 3
Classifier: Programming Language :: Python :: 3.6
Classifier: Programming Language :: Python :: 3.7
Classifier: Programming Language :: Python :: 3.8
Classifier: Programming Language :: Python :: 3.9
Requires-Dist: configalchemy
Provides-Extra: tests
Requires-Dist: fakeredis ; extra == 'tests'
Requires-Dist: dataclasses (>=0.6) ; (python_version < "3.7") and extra == 'tests'
